Metadata-Version: 2.1
Name: buildbot-enhanced-ui-improved
Version: 1.0.1
Summary: A clearer and faster to manipulate interface for the management of BuildBot builders
Home-page: UNKNOWN
Author: Marc Leonardi
Author-email: marc@goodbarber.com
License: UNKNOWN
Platform: UNKNOWN
